{"_type":"export","__export_format":4,"__export_date":"2025-01-25T19:45:12.893Z","__export_source":"insomnia.desktop.app:v10.3.0","resources":[{"_id":"req_8324acdbcdb34e2bb33104ab1fbca352","parentId":"wrk_b31751b6090a432da915ad59bbc1a696","modified":1737834271747,"created":1737834260949,"url":"http://127.0.0.1:8000/health","name":"New Request","description":"","method":"GET","body":{},"parameters":[],"headers":[{"name":"User-Agent","value":"insomnia/10.3.0"}],"authentication":{},"metaSortKey":-1737834260949,"isPrivate":false,"pathParameters":[],"settingStoreCookies":true,"settingSendCookies":true,"settingDisableRenderRequestBody":false,"settingEncodeUrl":true,"settingRebuildPath":true,"settingFollowRedirects":"global","_type":"request"},{"_id":"wrk_b31751b6090a432da915ad59bbc1a696","parentId":null,"modified":1737834035209,"created":1737834035209,"name":"knowledge-service","description":"","scope":"collection","_type":"workspace"},{"_id":"req_56f82c3d7e9c46e7ab6a8f6762e7db06","parentId":"wrk_b31751b6090a432da915ad59bbc1a696","modified":1737834102311,"created":1737834076468,"url":"http://127.0.0.1:8000/search?query=FastAPI&max_results=2","name":"New Request","description":"","method":"GET","body":{},"parameters":[],"headers":[{"name":"User-Agent","value":"insomnia/10.3.0"}],"authentication":{},"metaSortKey":-1737834076468,"isPrivate":false,"pathParameters":[],"settingStoreCookies":true,"settingSendCookies":true,"settingDisableRenderRequestBody":false,"settingEncodeUrl":true,"settingRebuildPath":true,"settingFollowRedirects":"global","_type":"request"},{"_id":"env_55803aaf3d6bcb919594d48bd59f3c5f2ce804ee","parentId":"wrk_b31751b6090a432da915ad59bbc1a696","modified":1737834035211,"created":1737834035211,"name":"Base Environment","data":{},"dataPropertyOrder":null,"color":null,"isPrivate":false,"metaSortKey":1737834035211,"environmentType":"kv","_type":"environment"},{"_id":"jar_55803aaf3d6bcb919594d48bd59f3c5f2ce804ee","parentId":"wrk_b31751b6090a432da915ad59bbc1a696","modified":1737834035212,"created":1737834035212,"name":"Default Jar","cookies":[],"_type":"cookie_jar"}]}